tklang/__init__.py
TkLang-0.2.6.dist-info/LICENSE
TkLang-0.2.6.dist-info/METADATA
TkLang-0.2.6.dist-info/WHEEL
TkLang-0.2.6.dist-info/top_level.txt
TkLang-0.2.6.dist-info/RECORD
