Metadata-Version: 2.1
Name: TkLang
Version: 0.2.6
Summary: For reading & writing .tk files
Home-page: https://www.beyonce.com
Author: hunterg
Author-email: redissuslolol@gmail.com
License: UNKNOWN
Platform: UNKNOWN
Classifier: Programming Language :: Python :: 3
Classifier: License :: OSI Approved :: MIT License
Classifier: Operating System :: OS Independent
Requires-Python: >=3.6
Requires-Dist: file-modes
Requires-Dist: getFN
